GlotScript/GlotScript.py
GlotScript/__init__.py
GlotScript-1.2.dist-info/LICENSE
GlotScript-1.2.dist-info/METADATA
GlotScript-1.2.dist-info/WHEEL
GlotScript-1.2.dist-info/top_level.txt
GlotScript-1.2.dist-info/RECORD
