Metadata-Version: 2.1
Name: GlotScript
Version: 1.2
Summary: A package for detecting the script (writing system) of given text.
Home-page: https://github.com/cisnlp/GlotScript
Author: Amir Hossein Kargaran
Author-email: kargaranamir@email.com
License: UNKNOWN
Platform: UNKNOWN
Classifier: License :: OSI Approved :: MIT License
Classifier: Programming Language :: Python :: 3
Classifier: Programming Language :: Python :: 3.6
Classifier: Programming Language :: Python :: 3.7
Classifier: Programming Language :: Python :: 3.8
Classifier: Programming Language :: Python :: 3.9
Classifier: Programming Language :: Python :: 3.10
